ext2term/__init__.py
ext2term/cli.py
ext2term/directory.py
ext2term/ext2.py
ext2term/group_descriptor.py
ext2term/inode.py
ext2term/io.py
ext2term/superblock.py
ext2term/terminal.py
ext2term-0.2.0.dist-info/LICENSE
ext2term-0.2.0.dist-info/METADATA
ext2term-0.2.0.dist-info/WHEEL
ext2term-0.2.0.dist-info/entry_points.txt
ext2term-0.2.0.dist-info/top_level.txt
ext2term-0.2.0.dist-info/RECORD
