Metadata-Version: 2.1
Name: ext2term
Version: 0.2.0
Summary: A CLI and library for navigating ext2 filesystems
Home-page: https://github.com/yourusername/ext2term
Author: William Guerrand
Author-email: guerrandw@gmail.com
License: BSD 2-Clause License
Keywords: ext2 filesystem
Classifier: Programming Language :: Python :: 3
Classifier: License :: OSI Approved :: MIT License
Classifier: Operating System :: OS Independent
Classifier: Topic :: Education
Classifier: Topic :: System :: Filesystems
Classifier: Intended Audience :: Developers
Classifier: Intended Audience :: Education
Requires-Python: >=3.4
License-File: LICENSE
